navdict/__init__.py
navdict/__main__.py
navdict/changed.py
navdict/directive.py
navdict/directive.pyi
navdict/directives.py
navdict/navdict.py
navdict/navdict.pyi
navdict/py.typed
navdict-0.6.3.dist-info/METADATA
navdict-0.6.3.dist-info/WHEEL
navdict-0.6.3.dist-info/entry_points.txt
navdict-0.6.3.dist-info/licenses/LICENSE
navdict-0.6.3.dist-info/RECORD
