Metadata-Version: 2.4
Name: navdict
Version: 0.6.3
Summary: A navigable dictionary with dot notation access and automatic file loading
Author: IvS KU Leuven
Maintainer-email: Rik Huygen <rik.huygen@kuleuven.be>
License-File: LICENSE
Classifier: Development Status :: 3 - Alpha
Classifier: Intended Audience :: Developers
Classifier: License :: OSI Approved :: MIT License
Classifier: Programming Language :: Python :: 3
Classifier: Programming Language :: Python :: 3.10
Classifier: Programming Language :: Python :: 3.11
Classifier: Programming Language :: Python :: 3.12
Classifier: Programming Language :: Python :: 3.13
Requires-Python: >=3.10
Requires-Dist: rich>=14.0.0
Requires-Dist: ruamel-yaml>=0.18.12
